SanauAutomationSDK/Worker.py
SanauAutomationSDK/__init__.py
SanauAutomationSDK/config.py
SanauAutomationSDK/api/Arm.py
SanauAutomationSDK/api/OneS.py
SanauAutomationSDK/api/Wrapper.py
SanauAutomationSDK/api/__init__.py
SanauAutomationSDK/api/arm/handlers/AlertsHandler.py
SanauAutomationSDK/api/arm/handlers/TasksHandler.py
SanauAutomationSDK/api/arm/handlers/__init__.py
SanauAutomationSDK/api/arm/models/Task.py
SanauAutomationSDK/classes/ArmApiCredentials.py
SanauAutomationSDK/controllers/JobsController.py
SanauAutomationSDK/utils/decorators.py
SanauAutomationSDK/utils/logutils.py
sanauautomationsdk-1.0.13.dist-info/METADATA
sanauautomationsdk-1.0.13.dist-info/WHEEL
sanauautomationsdk-1.0.13.dist-info/licenses/LICENSE
sanauautomationsdk-1.0.13.dist-info/RECORD
