Metadata-Version: 2.3
Name: SanauAutomationSDK
Version: 1.0.13
Summary: SDK that simplifies work with outsourcing
Project-URL: Homepage, https://github.com/sanau-kz/python-automation-sdk
Project-URL: Issues, https://github.com/sanau-kz/python-automation-sdk/issues
Author-email: "victor.ten" <prostobackoffice@gmail.com>, NotFakeL1eN <notfakel1en@gmail.com>, BaturinMaksim188 <Baturinmaksim188@gmail.com>
License-File: LICENSE
Classifier: License :: OSI Approved :: MIT License
Classifier: Operating System :: OS Independent
Classifier: Programming Language :: Python :: 3
Requires-Python: >=3.8
Requires-Dist: peewee
Requires-Dist: requests
